[{
    "number": "공지",
    "url": "https://russian.hallym.ac.kr/russian/community/notice.do?mode=view&articleNo=29832&article.offset=50&articleLimit=10",
    "date": "러시아학과관리자",
    "author": "Russian",
    "name": "[필독] 신종 코로나바이러스로 관련  2020-1학기 학사일정 변경 안내 자세히 보기"
}, {
    "number": "공지",
    "url": "https://russian.hallym.ac.kr/russian/community/notice.do?mode=view&articleNo=29740&article.offset=50&articleLimit=10",
    "date": "20.02.10",
    "author": "Russian",
    "name": "[필독] 러시아학과 오디세이세미나1~3교과목 개설학기 안내 자세히 보기"
}, {
    "number": "공지",
    "url": "https://russian.hallym.ac.kr/russian/community/notice.do?mode=view&articleNo=29739&article.offset=50&articleLimit=10",
    "date": "러시아학과관리자",
    "author": "Russian",
    "name": "[필독] 러시아학과 졸업기준 변경 안내 자세히 보기"
}, {
    "number": "공지",
    "url": "https://russian.hallym.ac.kr/russian/community/notice.do?mode=view&articleNo=27583&article.offset=50&articleLimit=10",
    "date": "20.02.06",
    "author": "Russian",
    "name": "영어졸업인증제 개편 안내 자세히 보기"
}, {
    "number": "공지",
    "url": "https://russian.hallym.ac.kr/russian/community/notice.do?mode=view&articleNo=22455&article.offset=50&articleLimit=10",
    "date": "러시아학과관리자",
    "author": "Russian",
    "name": "[필독] 공인어학성적 업로드 방법 자세히 보기"
}, {
    "number": "5",
    "url": "https://russian.hallym.ac.kr/russian/community/notice.do?mode=view&articleNo=22342&article.offset=50&articleLimit=10",
    "date": "20.02.06",
    "author": "Russian",
    "name": "2019학년도 1학기 전공 교과과정 변경 안내 자세히 보기"
}, {
    "number": "4",
    "url": "https://russian.hallym.ac.kr/russian/community/notice.do?mode=view&articleNo=22338&article.offset=50&articleLimit=10",
    "date": "러시아학과관리자",
    "author": "Russian",
    "name": "2019-2학기 파견 교환학생 선발 안내(중국,대만권 제외) 자세히 보기"
}, {
    "number": "3",
    "url": "https://russian.hallym.ac.kr/russian/community/notice.do?mode=view&articleNo=22335&article.offset=50&articleLimit=10",
    "date": "19.11.21",
    "author": "Russian",
    "name": "2018-2학기 TORFL(토르플) 지원금 안내 자세히 보기"
}, {
    "number": "2",
    "url": "https://russian.hallym.ac.kr/russian/community/notice.do?mode=view&articleNo=22332&article.offset=50&articleLimit=10",
    "date": "19.07.22",
    "author": "Russian",
    "name": "2018-2학기 러시아학과 졸업시험 안내  자세히 보기"
}, {
    "number": "1",
    "url": "https://russian.hallym.ac.kr/russian/community/notice.do?mode=view&articleNo=22328&article.offset=50&articleLimit=10",
    "date": "19.01.10",
    "author": "Russian",
    "name": "2019-1학기 러시아학과 교환학생 모집 자세히 보기"
}, {
    "number": "공지",
    "url": "https://russian.hallym.ac.kr/russian/community/notice.do?mode=view&articleNo=29832&article.offset=40&articleLimit=10",
    "date": "18.12.12",
    "author": "Russian",
    "name": "[필독] 신종 코로나바이러스로 관련  2020-1학기 학사일정 변경 안내 자세히 보기"
}, {
    "number": "공지",
    "url": "https://russian.hallym.ac.kr/russian/community/notice.do?mode=view&articleNo=29740&article.offset=40&articleLimit=10",
    "date": "18.09.12",
    "author": "Russian",
    "name": "[필독] 러시아학과 오디세이세미나1~3교과목 개설학기 안내 자세히 보기"
}, {
    "number": "공지",
    "url": "https://russian.hallym.ac.kr/russian/community/notice.do?mode=view&articleNo=29739&article.offset=40&articleLimit=10",
    "date": "18.09.07",
    "author": "Russian",
    "name": "[필독] 러시아학과 졸업기준 변경 안내 자세히 보기"
}, {
    "number": "공지",
    "url": "https://russian.hallym.ac.kr/russian/community/notice.do?mode=view&articleNo=27583&article.offset=40&articleLimit=10",
    "date": "18.09.07",
    "author": "Russian",
    "name": "영어졸업인증제 개편 안내 자세히 보기"
}, {
    "number": "공지",
    "url": "https://russian.hallym.ac.kr/russian/community/notice.do?mode=view&articleNo=22455&article.offset=40&articleLimit=10",
    "date": "러시아학과관리자",
    "author": "Russian",
    "name": "[필독] 공인어학성적 업로드 방법 자세히 보기"
}, {
    "number": "15",
    "url": "https://russian.hallym.ac.kr/russian/community/notice.do?mode=view&articleNo=22385&article.offset=40&articleLimit=10",
    "date": "20.02.10",
    "author": "Russian",
    "name": "2019-1학기 상생러닝 디딤돌 프로그램 시행 안내  자세히 보기"
}, {
    "number": "14",
    "url": "https://russian.hallym.ac.kr/russian/community/notice.do?mode=view&articleNo=22381&article.offset=40&articleLimit=10",
    "date": "러시아학과관리자",
    "author": "Russian",
    "name": "오디세이 학습설계 메뉴얼 안내 자세히 보기"
}, {
    "number": "13",
    "url": "https://russian.hallym.ac.kr/russian/community/notice.do?mode=view&articleNo=22378&article.offset=40&articleLimit=10",
    "date": "20.02.06",
    "author": "Russian",
    "name": "2019-1학기 한림멘토링 멘토/멘티 모집 안내 자세히 보기"
}, {
    "number": "12",
    "url": "https://russian.hallym.ac.kr/russian/community/notice.do?mode=view&articleNo=22375&article.offset=40&articleLimit=10",
    "date": "러시아학과관리자",
    "author": "Russian",
    "name": "[필독] 2019학년도 1학기 공결신청 안내 자세히 보기"
}, {
    "number": "11",
    "url": "https://russian.hallym.ac.kr/russian/community/notice.do?mode=view&articleNo=22370&article.offset=40&articleLimit=10",
    "date": "20.02.06",
    "author": "Russian",
    "name": "[필독] 2019학년도 러시아학과 신입생 오리엔테이션 안내 자세히 보기"
}, {
    "number": "10",
    "url": "https://russian.hallym.ac.kr/russian/community/notice.do?mode=view&articleNo=22365&article.offset=40&articleLimit=10",
    "date": "러시아학과관리자",
    "author": "Russian",
    "name": "[필독] 2019학년도 신입생 대상 'MBTI 및 STRONG검사' 시행방법 및 일정 안내 자세히 보기"
}, {
    "number": "9",
    "url": "https://russian.hallym.ac.kr/russian/community/notice.do?mode=view&articleNo=22359&article.offset=40&articleLimit=10",
    "date": "19.11.21",
    "author": "Russian",
    "name": "[필독] 신입생 수강신청 일정 및 수강신청,전자출결 사용 메뉴얼 안내 자세히 보기"
}, {
    "number": "8",
    "url": "https://russian.hallym.ac.kr/russian/community/notice.do?mode=view&articleNo=22355&article.offset=40&articleLimit=10",
    "date": "19.07.22",
    "author": "Russian",
    "name": "[필독] 2019년도 신입생 모바일 학생증 발급 안내 자세히 보기"
}, {
    "number": "7",
    "url": "https://russian.hallym.ac.kr/russian/community/notice.do?mode=view&articleNo=22350&article.offset=40&articleLimit=10",
    "date": "19.02.26",
    "author": "Russian",
    "name": "동계 학위수여식 학사가운 대여 안내 (2019.02.20) 자세히 보기"
}, {
    "number": "6",
    "url": "https://russian.hallym.ac.kr/russian/community/notice.do?mode=view&articleNo=22346&article.offset=40&articleLimit=10",
    "date": "19.02.26",
    "author": "Russian",
    "name": "2019-1학기 러시아학과 고급러시아어 교과목 관련 안내 자세히 보기"
}, {
    "number": "공지",
    "url": "https://russian.hallym.ac.kr/russian/community/notice.do?mode=view&articleNo=29832&article.offset=30&articleLimit=10",
    "date": "19.02.25",
    "author": "Russian",
    "name": "[필독] 신종 코로나바이러스로 관련  2020-1학기 학사일정 변경 안내 자세히 보기"
}, {
    "number": "공지",
    "url": "https://russian.hallym.ac.kr/russian/community/notice.do?mode=view&articleNo=29740&article.offset=30&articleLimit=10",
    "date": "19.02.22",
    "author": "Russian",
    "name": "[필독] 러시아학과 오디세이세미나1~3교과목 개설학기 안내 자세히 보기"
}, {
    "number": "공지",
    "url": "https://russian.hallym.ac.kr/russian/community/notice.do?mode=view&articleNo=29739&article.offset=30&articleLimit=10",
    "date": "19.02.21",
    "author": "Russian",
    "name": "[필독] 러시아학과 졸업기준 변경 안내 자세히 보기"
}, {
    "number": "공지",
    "url": "https://russian.hallym.ac.kr/russian/community/notice.do?mode=view&articleNo=27583&article.offset=30&articleLimit=10",
    "date": "19.02.21",
    "author": "Russian",
    "name": "영어졸업인증제 개편 안내 자세히 보기"
}, {
    "number": "공지",
    "url": "https://russian.hallym.ac.kr/russian/community/notice.do?mode=view&articleNo=22455&article.offset=30&articleLimit=10",
    "date": "19.02.21",
    "author": "Russian",
    "name": "[필독] 공인어학성적 업로드 방법 자세히 보기"
}, {
    "number": "25",
    "url": "https://russian.hallym.ac.kr/russian/community/notice.do?mode=view&articleNo=22427&article.offset=30&articleLimit=10",
    "date": "19.02.21",
    "author": "Russian",
    "name": "2019 돗토리대학 하계 단기연수 참가자 모집 안내 자세히 보기"
}, {
    "number": "24",
    "url": "https://russian.hallym.ac.kr/russian/community/notice.do?mode=view&articleNo=22424&article.offset=30&articleLimit=10",
    "date": "19.02.08",
    "author": "Russian",
    "name": "2019-1학기 TORFL(토르플) 지원금 안내 자세히 보기"
}, {
    "number": "23",
    "url": "https://russian.hallym.ac.kr/russian/community/notice.do?mode=view&articleNo=22421&article.offset=30&articleLimit=10",
    "date": "19.02.07",
    "author": "Russian",
    "name": "2019학년도 신·편입생 학생증(스마트카드) 배부안내 자세히 보기"
}, {
    "number": "22",
    "url": "https://russian.hallym.ac.kr/russian/community/notice.do?mode=view&articleNo=22415&article.offset=30&articleLimit=10",
    "date": "러시아학과관리자",
    "author": "Russian",
    "name": "[한림봉사센터] 2019 한림봉사단 모집 안내 자세히 보기"
}, {
    "number": "21",
    "url": "https://russian.hallym.ac.kr/russian/community/notice.do?mode=view&articleNo=22412&article.offset=30&articleLimit=10",
    "date": "20.02.10",
    "author": "Russian",
    "name": "2019-2학기 러시아학과 현지교육 연수생 모집 자세히 보기"
}, {
    "number": "20",
    "url": "https://russian.hallym.ac.kr/russian/community/notice.do?mode=view&articleNo=22406&article.offset=30&articleLimit=10",
    "date": "러시아학과관리자",
    "author": "Russian",
    "name": "2019-2학기 러시아학과 교환학생 모집 자세히 보기"
}, {
    "number": "19",
    "url": "https://russian.hallym.ac.kr/russian/community/notice.do?mode=view&articleNo=22403&article.offset=30&articleLimit=10",
    "date": "20.02.06",
    "author": "Russian",
    "name": "2019학년도 1학기 수강철회 및 대체재이수 안내  자세히 보기"
}, {
    "number": "18",
    "url": "https://russian.hallym.ac.kr/russian/community/notice.do?mode=view&articleNo=22399&article.offset=30&articleLimit=10",
    "date": "러시아학과관리자",
    "author": "Russian",
    "name": "2019학년도 학생예비군 대원 전입신고 안내 자세히 보기"
}, {
    "number": "17",
    "url": "https://russian.hallym.ac.kr/russian/community/notice.do?mode=view&articleNo=22393&article.offset=30&articleLimit=10",
    "date": "20.02.06",
    "author": "Russian",
    "name": "대학생 근현대사 탐방경연대회 안내 자세히 보기"
}, {
    "number": "16",
    "url": "https://russian.hallym.ac.kr/russian/community/notice.do?mode=view&articleNo=22390&article.offset=30&articleLimit=10",
    "date": "러시아학과관리자",
    "author": "Russian",
    "name": "2019-1학기 현장실습 전공학점 인정 기준 안내 자세히 보기"
}, {
    "number": "공지",
    "url": "https://russian.hallym.ac.kr/russian/community/notice.do?mode=view&articleNo=29832&article.offset=20&articleLimit=10",
    "date": "19.11.21",
    "author": "Russian",
    "name": "[필독] 신종 코로나바이러스로 관련  2020-1학기 학사일정 변경 안내 자세히 보기"
}, {
    "number": "공지",
    "url": "https://russian.hallym.ac.kr/russian/community/notice.do?mode=view&articleNo=29740&article.offset=20&articleLimit=10",
    "date": "19.07.22",
    "author": "Russian",
    "name": "[필독] 러시아학과 오디세이세미나1~3교과목 개설학기 안내 자세히 보기"
}, {
    "number": "공지",
    "url": "https://russian.hallym.ac.kr/russian/community/notice.do?mode=view&articleNo=29739&article.offset=20&articleLimit=10",
    "date": "19.03.28",
    "author": "Russian",
    "name": "[필독] 러시아학과 졸업기준 변경 안내 자세히 보기"
}, {
    "number": "공지",
    "url": "https://russian.hallym.ac.kr/russian/community/notice.do?mode=view&articleNo=27583&article.offset=20&articleLimit=10",
    "date": "19.03.27",
    "author": "Russian",
    "name": "영어졸업인증제 개편 안내 자세히 보기"
}, {
    "number": "공지",
    "url": "https://russian.hallym.ac.kr/russian/community/notice.do?mode=view&articleNo=22455&article.offset=20&articleLimit=10",
    "date": "19.03.20",
    "author": "Russian",
    "name": "[필독] 공인어학성적 업로드 방법 자세히 보기"
}, {
    "number": "35",
    "url": "https://russian.hallym.ac.kr/russian/community/notice.do?mode=view&articleNo=22467&article.offset=20&articleLimit=10",
    "date": "19.03.13",
    "author": "Russian",
    "name": "2019-2학기 한림멘토링 멘토/멘티 모집 안내 자세히 보기"
}, {
    "number": "34",
    "url": "https://russian.hallym.ac.kr/russian/community/notice.do?mode=view&articleNo=22460&article.offset=20&articleLimit=10",
    "date": "19.03.08",
    "author": "Russian",
    "name": "[홍보] 2019년 제 4회 의료통역능력검정시험 실시 안내 자세히 보기"
}, {
    "number": "33",
    "url": "https://russian.hallym.ac.kr/russian/community/notice.do?mode=view&articleNo=22458&article.offset=20&articleLimit=10",
    "date": "19.03.08",
    "author": "Russian",
    "name": "[필독] 2019년 8월 졸업예정자 졸업판정 결과 조회 안내 자세히 보기"
}, {
    "number": "32",
    "url": "https://russian.hallym.ac.kr/russian/community/notice.do?mode=view&articleNo=22452&article.offset=20&articleLimit=10",
    "date": "19.03.08",
    "author": "Russian",
    "name": "[필독] 러시아학과(전필) 오디세이세미나3 교과목 수강신청 안내 자세히 보기"
}, {
    "number": "31",
    "url": "https://russian.hallym.ac.kr/russian/community/notice.do?mode=view&articleNo=22448&article.offset=20&articleLimit=10",
    "date": "19.03.08",
    "author": "Russian",
    "name": "2019년 8월 졸업 관련 안내 자세히 보기"
}, {
    "number": "30",
    "url": "https://russian.hallym.ac.kr/russian/community/notice.do?mode=view&articleNo=22444&article.offset=20&articleLimit=10",
    "date": "19.03.07",
    "author": "Russian",
    "name": "2020-1학기 러시아 극동국립대학교 파견 교환학생 모집 안내 자세히 보기"
}, {
    "number": "29",
    "url": "https://russian.hallym.ac.kr/russian/community/notice.do?mode=view&articleNo=22441&article.offset=20&articleLimit=10",
    "date": "19.02.27",
    "author": "Russian",
    "name": "[홍보] 2019년도 제2차 국립수산물품질관리원 공무직 등 근로자 채용 공고 안내 자세히 보기"
}, {
    "number": "28",
    "url": "https://russian.hallym.ac.kr/russian/community/notice.do?mode=view&articleNo=22437&article.offset=20&articleLimit=10",
    "date": "러시아학과관리자",
    "author": "Russian",
    "name": "[홍보] 2019 유라시아 청년 아카데미  안내 자세히 보기"
}, {
    "number": "27",
    "url": "https://russian.hallym.ac.kr/russian/community/notice.do?mode=view&articleNo=22434&article.offset=20&articleLimit=10",
    "date": "20.02.10",
    "author": "Russian",
    "name": "2019-2학기 러시아학과 현지교육 연수생 서류제출 안내 자세히 보기"
}, {
    "number": "26",
    "url": "https://russian.hallym.ac.kr/russian/community/notice.do?mode=view&articleNo=22431&article.offset=20&articleLimit=10",
    "date": "러시아학과관리자",
    "author": "Russian",
    "name": "2019-1학기 러시아학과 졸업시험 안내 자세히 보기"
}, {
    "number": "공지",
    "url": "https://russian.hallym.ac.kr/russian/community/notice.do?mode=view&articleNo=29832&article.offset=10&articleLimit=10",
    "date": "20.02.06",
    "author": "Russian",
    "name": "[필독] 신종 코로나바이러스로 관련  2020-1학기 학사일정 변경 안내 자세히 보기"
}, {
    "number": "공지",
    "url": "https://russian.hallym.ac.kr/russian/community/notice.do?mode=view&articleNo=29740&article.offset=10&articleLimit=10",
    "date": "러시아학과관리자",
    "author": "Russian",
    "name": "[필독] 러시아학과 오디세이세미나1~3교과목 개설학기 안내 자세히 보기"
}, {
    "number": "공지",
    "url": "https://russian.hallym.ac.kr/russian/community/notice.do?mode=view&articleNo=29739&article.offset=10&articleLimit=10",
    "date": "20.02.06",
    "author": "Russian",
    "name": "[필독] 러시아학과 졸업기준 변경 안내 자세히 보기"
}, {
    "number": "공지",
    "url": "https://russian.hallym.ac.kr/russian/community/notice.do?mode=view&articleNo=27583&article.offset=10&articleLimit=10",
    "date": "러시아학과관리자",
    "author": "Russian",
    "name": "영어졸업인증제 개편 안내 자세히 보기"
}, {
    "number": "공지",
    "url": "https://russian.hallym.ac.kr/russian/community/notice.do?mode=view&articleNo=22455&article.offset=10&articleLimit=10",
    "date": "19.11.21",
    "author": "Russian",
    "name": "[필독] 공인어학성적 업로드 방법 자세히 보기"
}, {
    "number": "45",
    "url": "https://russian.hallym.ac.kr/russian/community/notice.do?mode=view&articleNo=28379&article.offset=10&articleLimit=10",
    "date": "19.07.22",
    "author": "Russian",
    "name": "한림대학교 인문대교학팀 러시아학과 학사조교 채용 공고 자세히 보기"
}, {
    "number": "44",
    "url": "https://russian.hallym.ac.kr/russian/community/notice.do?mode=view&articleNo=27306&article.offset=10&articleLimit=10",
    "date": "19.08.14",
    "author": "Russian",
    "name": "[홍보]★2019 대학일자리센터 청년정책체감도 및 만족도 조사★ 자세히 보기"
}, {
    "number": "43",
    "url": "https://russian.hallym.ac.kr/russian/community/notice.do?mode=view&articleNo=27305&article.offset=10&articleLimit=10",
    "date": "19.08.12",
    "author": "Russian",
    "name": "[공지] 2020학년도 1학기 학생생활관 3관(HID)'러시아어' 신입사생 모집 안내  자세히 보기"
}, {
    "number": "42",
    "url": "https://russian.hallym.ac.kr/russian/community/notice.do?mode=view&articleNo=26866&article.offset=10&articleLimit=10",
    "date": "19.08.05",
    "author": "Russian",
    "name": "[홍보]인문학 홍보이미지 및 CI디자인 공모전 자세히 보기"
}, {
    "number": "41",
    "url": "https://russian.hallym.ac.kr/russian/community/notice.do?mode=view&articleNo=26781&article.offset=10&articleLimit=10",
    "date": "19.07.22",
    "author": "Russian",
    "name": "[홍보]러시아사진 공모전-열림과 나눔의 인문학축제- 자세히 보기"
}, {
    "number": "40",
    "url": "https://russian.hallym.ac.kr/russian/community/notice.do?mode=view&articleNo=26779&article.offset=10&articleLimit=10",
    "date": "19.07.12",
    "author": "Russian",
    "name": "[홍보]UCC콘테스트\"러시아다시보기\"-열림과 나눔의 인문학축제- 자세히 보기"
}, {
    "number": "39",
    "url": "https://russian.hallym.ac.kr/russian/community/notice.do?mode=view&articleNo=26066&article.offset=10&articleLimit=10",
    "date": "19.04.30",
    "author": "Russian",
    "name": "2019-2학기 TORFL(토르플) 지원금 안내 자세히 보기"
}, {
    "number": "38",
    "url": "https://russian.hallym.ac.kr/russian/community/notice.do?mode=view&articleNo=23926&article.offset=10&articleLimit=10",
    "date": "19.04.23",
    "author": "Russian",
    "name": "2019-2학기 러시아학과 졸업시험 안내 자세히 보기"
}, {
    "number": "37",
    "url": "https://russian.hallym.ac.kr/russian/community/notice.do?mode=view&articleNo=23925&article.offset=10&articleLimit=10",
    "date": "19.04.23",
    "author": "Russian",
    "name": "[필독] 2019-2학기 오디세이세미나2(리더십과 기업가정신) 외부강사 특강일정 안내 자세히 보기"
}, {
    "number": "36",
    "url": "https://russian.hallym.ac.kr/russian/community/notice.do?mode=view&articleNo=22470&article.offset=10&articleLimit=10",
    "date": "19.04.12",
    "author": "Russian",
    "name": "[필독] 2019학년도 2학기 학생예비군 전입신고 안내 자세히 보기"
}, {
    "number": "공지",
    "url": "https://russian.hallym.ac.kr/russian/community/notice.do?mode=view&articleNo=29832&article.offset=0&articleLimit=10",
    "date": "19.04.03",
    "author": "Russian",
    "name": "[필독] 신종 코로나바이러스로 관련  2020-1학기 학사일정 변경 안내 자세히 보기"
}, {
    "number": "공지",
    "url": "https://russian.hallym.ac.kr/russian/community/notice.do?mode=view&articleNo=29740&article.offset=0&articleLimit=10",
    "date": "러시아학과관리자",
    "author": "Russian",
    "name": "[필독] 러시아학과 오디세이세미나1~3교과목 개설학기 안내 자세히 보기"
}, {
    "number": "공지",
    "url": "https://russian.hallym.ac.kr/russian/community/notice.do?mode=view&articleNo=29739&article.offset=0&articleLimit=10",
    "date": "20.02.10",
    "author": "Russian",
    "name": "[필독] 러시아학과 졸업기준 변경 안내 자세히 보기"
}, {
    "number": "공지",
    "url": "https://russian.hallym.ac.kr/russian/community/notice.do?mode=view&articleNo=27583&article.offset=0&articleLimit=10",
    "date": "러시아학과관리자",
    "author": "Russian",
    "name": "영어졸업인증제 개편 안내 자세히 보기"
}, {
    "number": "공지",
    "url": "https://russian.hallym.ac.kr/russian/community/notice.do?mode=view&articleNo=22455&article.offset=0&articleLimit=10",
    "date": "20.02.06",
    "author": "Russian",
    "name": "[필독] 공인어학성적 업로드 방법 자세히 보기"
}, {
    "number": "55",
    "url": "https://russian.hallym.ac.kr/russian/community/notice.do?mode=view&articleNo=32103&article.offset=0&articleLimit=10",
    "date": "러시아학과관리자",
    "author": "Russian",
    "name": "2020-1학기 TORFL(토르플) 지원금 안내 자세히 보기"
}, {
    "number": "54",
    "url": "https://russian.hallym.ac.kr/russian/community/notice.do?mode=view&articleNo=31459&article.offset=0&articleLimit=10",
    "date": "20.02.06",
    "author": "Russian",
    "name": "[홍보]2020 유라시아 아카데미 모집요강 자세히 보기"
}, {
    "number": "53",
    "url": "https://russian.hallym.ac.kr/russian/community/notice.do?mode=view&articleNo=31451&article.offset=0&articleLimit=10",
    "date": "러시아학과관리자",
    "author": "Russian",
    "name": "2020-1학기 러시아학과 졸업시험 안내 자세히 보기"
}, {
    "number": "52",
    "url": "https://russian.hallym.ac.kr/russian/community/notice.do?mode=view&articleNo=31332&article.offset=0&articleLimit=10",
    "date": "19.11.21",
    "author": "Russian",
    "name": "[홍보] 취업역량강화멘토링(취업스터디) 신청자 모집 자세히 보기"
}, {
    "number": "51",
    "url": "https://russian.hallym.ac.kr/russian/community/notice.do?mode=view&articleNo=31306&article.offset=0&articleLimit=10",
    "date": "19.07.22",
    "author": "Russian",
    "name": "[홍보] 제10회 전국 러시아어 토론대회 자세히 보기"
}, {
    "number": "50",
    "url": "https://russian.hallym.ac.kr/russian/community/notice.do?mode=view&articleNo=31136&article.offset=0&articleLimit=10",
    "date": "러시아학과관리자",
    "author": "Russian",
    "name": "[홍보] 2020년도 제7기 강원 MICE 서포터즈 G-MICE KEY 모집 자세히 보기"
}, {
    "number": "49",
    "url": "https://russian.hallym.ac.kr/russian/community/notice.do?mode=view&articleNo=30392&article.offset=0&articleLimit=10",
    "date": "19.12.13",
    "author": "Russian",
    "name": "2020-1학기 러시아학과 한림 멘토링 (멘토, 멘티) 모집 안내 자세히 보기"
}, {
    "number": "48",
    "url": "https://russian.hallym.ac.kr/russian/community/notice.do?mode=view&articleNo=30390&article.offset=0&articleLimit=10",
    "date": "러시아학과관리자",
    "author": "Russian",
    "name": "코로나19로인한 2020년 1학기 휴학 및 자퇴 안내 재공지 자세히 보기"
}, {
    "number": "47",
    "url": "https://russian.hallym.ac.kr/russian/community/notice.do?mode=view&articleNo=30325&article.offset=0&articleLimit=10",
    "date": "19.11.13",
    "author": "Russian",
    "name": "2020학년도 러시아학과 신/편입생 오리엔테이션 안내 자세히 보기"
}, {
    "number": "46",
    "url": "https://russian.hallym.ac.kr/russian/community/notice.do?mode=view&articleNo=28780&article.offset=0&articleLimit=10",
    "date": "러시아학과관리자",
    "author": "Russian",
    "name": "2020-2학기 러시아 극동국립대학교 파견 교환학생 모집 안내 자세히 보기"
}]